siammask/__init__.py
siammask/siammask.py
siammask/model/__init__.py
siammask/model/adjuster.py
siammask/model/base.py
siammask/model/convolution.py
siammask/model/mask_refinement.py
siammask/model/proposal_network.py
siammask/model/resnet.py
tf_siammask-1.0.4.dist-info/LICENSE
tf_siammask-1.0.4.dist-info/METADATA
tf_siammask-1.0.4.dist-info/WHEEL
tf_siammask-1.0.4.dist-info/top_level.txt
tf_siammask-1.0.4.dist-info/zip-safe
tf_siammask-1.0.4.dist-info/RECORD
