Metadata-Version: 2.1
Name: tf-siammask
Version: 1.0.4
Summary: SiamMask implementation by Tensorflow 2
Home-page: https://github.com/Licht-T/tf-siammask
License: MIT
Keywords: siammask,tensorflow
Platform: UNKNOWN
Classifier: Topic :: Scientific/Engineering :: Image Recognition
Classifier: License :: OSI Approved :: MIT License
Classifier: Programming Language :: Python :: 3
Requires-Dist: pillow
Requires-Dist: tensorflow
Requires-Dist: numpy
